piso.v
// PISO - Parallel In Serial Out (Shift Left & Shift Right)
module piso(
    input clk, reset,
    input load,           // 1 = load parallel data, 0 = shift
    input shift_dir,      // 0 = shift left, 1 = shift right
    input [7:0] parallel_in,
    output reg serial_out,
    output reg [7:0] reg_state
);
    always @(posedge clk or posedge reset) begin
        if(reset) begin
            reg_state  <= 8'b0;
            serial_out <= 0;
        end
        else if(load) begin
            reg_state  <= parallel_in;  // load parallel data
            serial_out <= 0;
        end
        else begin
            if(shift_dir == 0) begin
                serial_out <= reg_state[7];           // MSB out
                reg_state  <= {reg_state[6:0], 1'b0}; // shift left
            end else begin
                serial_out <= reg_state[0];           // LSB out
                reg_state  <= {1'b0, reg_state[7:1]}; // shift right
            end
        end
    end
endmodule

sipo.v
// SIPO - Serial In Parallel Out (Shift Left & Shift Right)
module sipo(
    input clk, reset,
    input serial_in,
    input shift_dir,      // 0 = shift left, 1 = shift right
    output reg [7:0] parallel_out
);
    always @(posedge clk or posedge reset) begin
        if(reset)
            parallel_out <= 8'b0;
        else if(shift_dir == 0)
            parallel_out <= {parallel_out[6:0], serial_in};  // shift left
        else
            parallel_out <= {serial_in, parallel_out[7:1]};  // shift right
    end
endmodule

shift_register_tb.v
`timescale 1ns/1ns

module shift_register_tb;

    // ---- SIPO signals ----
    reg clk, reset;
    reg serial_in, shift_dir;
    wire [7:0] sipo_out;

    // ---- PISO signals ----
    reg load;
    reg [7:0] parallel_in;
    wire piso_serial_out;
    wire [7:0] piso_state;

    // Instantiate SIPO
    sipo SIPO_inst(
        .clk(clk), .reset(reset),
        .serial_in(serial_in),
        .shift_dir(shift_dir),
        .parallel_out(sipo_out)
    );

    // Instantiate PISO
    piso PISO_inst(
        .clk(clk), .reset(reset),
        .load(load),
        .shift_dir(shift_dir),
        .parallel_in(parallel_in),
        .serial_out(piso_serial_out),
        .reg_state(piso_state)
    );

    // Clock: toggle every 5ns -> 10ns period
    always #5 clk = ~clk;

    integer i;

    initial begin
        $dumpfile("shift_register.vcd");
        $dumpvars(0, shift_register_tb);

        // Init
        clk = 0; reset = 1; serial_in = 0;
        shift_dir = 0; load = 0; parallel_in = 8'b0;
        #10 reset = 0;

        // ============================================
        // SIPO - SHIFT LEFT
        // Serially input 1,0,1,1,0,0,1,1 -> expect 10110011
        // ============================================
        $display("\n--- SIPO Shift LEFT ---");
        shift_dir = 0;
        begin
            serial_in = 1; #10; $display("SIPO SL: serial_in=%b -> parallel_out=%b", serial_in, sipo_out);
            serial_in = 0; #10; $display("SIPO SL: serial_in=%b -> parallel_out=%b", serial_in, sipo_out);
            serial_in = 1; #10; $display("SIPO SL: serial_in=%b -> parallel_out=%b", serial_in, sipo_out);
            serial_in = 1; #10; $display("SIPO SL: serial_in=%b -> parallel_out=%b", serial_in, sipo_out);
            serial_in = 0; #10; $display("SIPO SL: serial_in=%b -> parallel_out=%b", serial_in, sipo_out);
            serial_in = 0; #10; $display("SIPO SL: serial_in=%b -> parallel_out=%b", serial_in, sipo_out);
            serial_in = 1; #10; $display("SIPO SL: serial_in=%b -> parallel_out=%b", serial_in, sipo_out);
            serial_in = 1; #10; $display("SIPO SL: serial_in=%b -> parallel_out=%b", serial_in, sipo_out);
        end

        // Reset before next test
        reset = 1; #10; reset = 0;

        // ============================================
        // SIPO - SHIFT RIGHT
        // ============================================
        $display("\n--- SIPO Shift RIGHT ---");
        shift_dir = 1;
        begin
            serial_in = 1; #10; $display("SIPO SR: serial_in=%b -> parallel_out=%b", serial_in, sipo_out);
            serial_in = 1; #10; $display("SIPO SR: serial_in=%b -> parallel_out=%b", serial_in, sipo_out);
            serial_in = 0; #10; $display("SIPO SR: serial_in=%b -> parallel_out=%b", serial_in, sipo_out);
            serial_in = 0; #10; $display("SIPO SR: serial_in=%b -> parallel_out=%b", serial_in, sipo_out);
            serial_in = 1; #10; $display("SIPO SR: serial_in=%b -> parallel_out=%b", serial_in, sipo_out);
            serial_in = 1; #10; $display("SIPO SR: serial_in=%b -> parallel_out=%b", serial_in, sipo_out);
            serial_in = 0; #10; $display("SIPO SR: serial_in=%b -> parallel_out=%b", serial_in, sipo_out);
            serial_in = 1; #10; $display("SIPO SR: serial_in=%b -> parallel_out=%b", serial_in, sipo_out);
        end

        // Reset before PISO
        reset = 1; #10; reset = 0;

        // ============================================
        // PISO - SHIFT LEFT
        // Load 10110011, then shift out serially
        // ============================================
        $display("\n--- PISO Shift LEFT (load=10110011) ---");
        shift_dir = 0;
        parallel_in = 8'b10110011;
        load = 1; #10; load = 0;
        $display("PISO loaded: reg_state=%b", piso_state);
        for(i = 0; i < 8; i = i+1) begin
            #10;
            $display("PISO SL: serial_out=%b | reg_state=%b", piso_serial_out, piso_state);
        end

        // Reset before next PISO test
        reset = 1; #10; reset = 0;

        // ============================================
        // PISO - SHIFT RIGHT
        // Load 11001010, then shift out serially
        // ============================================
        $display("\n--- PISO Shift RIGHT (load=11001010) ---");
        shift_dir = 1;
        parallel_in = 8'b11001010;
        load = 1; #10; load = 0;
        $display("PISO loaded: reg_state=%b", piso_state);
        for(i = 0; i < 8; i = i+1) begin
            #10;
            $display("PISO SR: serial_out=%b | reg_state=%b", piso_serial_out, piso_state);
        end

        $finish;
    end

endmodule

shift_register.vcd
$date
	Sat Apr 25 20:58:07 2026
$end
$version
	ModelSim Version 2020.1
$end
$timescale
	1ns
$end

$scope module shift_register_tb $end
$var reg 1 ! clk $end
$var reg 1 " reset $end
$var reg 1 # serial_in $end
$var reg 1 $ shift_dir $end
$var wire 1 % sipo_out [7] $end
$var wire 1 & sipo_out [6] $end
$var wire 1 ' sipo_out [5] $end
$var wire 1 ( sipo_out [4] $end
$var wire 1 ) sipo_out [3] $end
$var wire 1 * sipo_out [2] $end
$var wire 1 + sipo_out [1] $end
$var wire 1 , sipo_out [0] $end
$var reg 1 - load $end
$var reg 8 . parallel_in [7:0] $end
$var wire 1 / piso_serial_out $end
$var wire 1 0 piso_state [7] $end
$var wire 1 1 piso_state [6] $end
$var wire 1 2 piso_state [5] $end
$var wire 1 3 piso_state [4] $end
$var wire 1 4 piso_state [3] $end
$var wire 1 5 piso_state [2] $end
$var wire 1 6 piso_state [1] $end
$var wire 1 7 piso_state [0] $end
$var integer 32 8 i $end

$scope module SIPO_inst $end
$var wire 1 9 clk $end
$var wire 1 : reset $end
$var wire 1 ; serial_in $end
$var wire 1 < shift_dir $end
$var reg 8 = parallel_out [7:0] $end
$upscope $end

$scope module PISO_inst $end
$var wire 1 > clk $end
$var wire 1 ? reset $end
$var wire 1 @ load $end
$var wire 1 A shift_dir $end
$var wire 1 B parallel_in [7] $end
$var wire 1 C parallel_in [6] $end
$var wire 1 D parallel_in [5] $end
$var wire 1 E parallel_in [4] $end
$var wire 1 F parallel_in [3] $end
$var wire 1 G parallel_in [2] $end
$var wire 1 H parallel_in [1] $end
$var wire 1 I parallel_in [0] $end
$var reg 1 J serial_out $end
$var reg 8 K reg_state [7:0] $end
$upscope $end
$upscope $end
$enddefinitions $end
#0
$dumpvars
0!
1"
0#
0$
0-
b0 .
b0 =
0J
b0 K
bx 8
0,
0+
0*
0)
0(
0'
0&
0%
0/
07
06
05
04
03
02
01
00
0I
0H
0G
0F
0E
0D
0C
0B
0A
0@
1?
0>
0<
0;
1:
09
$end
#5
1!
19
1>
#10
0"
1#
0!
1;
0:
0?
09
0>
#15
1!
19
1>
b1 =
1,
#20
0#
0!
0;
09
0>
#25
1!
19
1>
b10 =
0,
1+
#30
1#
0!
1;
09
0>
#35
1!
19
1>
b101 =
1,
0+
1*
#40
0!
09
0>
#45
1!
19
1>
b1011 =
1+
0*
1)
#50
0#
0!
0;
09
0>
#55
1!
19
1>
b10110 =
0,
1*
0)
1(
#60
0!
09
0>
#65
1!
19
1>
b101100 =
0+
1)
0(
1'
#70
1#
0!
1;
09
0>
#75
1!
19
1>
b1011001 =
1,
0*
1(
0'
1&
#80
0!
09
0>
#85
1!
19
1>
b10110011 =
1+
0)
1'
0&
1%
#90
1"
0!
1:
1?
09
0>
b0 =
0,
0+
0(
0'
0%
#95
1!
19
1>
#100
0"
1$
0!
1<
1A
0:
0?
09
0>
#105
1!
19
1>
b10000000 =
1%
#110
0!
09
0>
#115
1!
19
1>
b11000000 =
1&
#120
0#
0!
0;
09
0>
#125
1!
19
1>
b1100000 =
1'
0%
#130
0!
09
0>
#135
1!
19
1>
b110000 =
1(
0&
#140
1#
0!
1;
09
0>
#145
1!
19
1>
b10011000 =
1)
0'
1%
#150
0!
09
0>
#155
1!
19
1>
b11001100 =
1*
0(
1&
#160
0#
0!
0;
09
0>
#165
1!
19
1>
b1100110 =
1+
0)
1'
0%
#170
1#
0!
1;
09
0>
#175
1!
19
1>
b10110011 =
1,
0*
1(
0&
1%
#180
1"
0!
1:
1?
09
0>
b0 =
0,
0+
0(
0'
0%
#185
1!
19
1>
#190
0"
0$
b10110011 .
1-
0!
0<
0A
1I
1H
1E
1D
1B
1@
0:
0?
09
0>
#195
1!
19
1>
b10110011 K
b1 =
1,
17
16
13
12
10
#200
0-
b0 8
0!
0@
09
0>
#205
1!
19
1>
1J
b1100110 K
b11 =
1/
1+
07
15
03
11
00
#210
b1 8
0!
09
0>
#215
1!
19
1>
0J
b11001100 K
b111 =
0/
1*
06
14
02
10
#220
b10 8
0!
09
0>
#225
1!
19
1>
1J
b10011000 K
b1111 =
1/
1)
05
13
01
#230
b11 8
0!
09
0>
#235
1!
19
1>
b110000 K
b11111 =
1(
04
12
00
#240
b100 8
0!
09
0>
#245
1!
19
1>
0J
b1100000 K
b111111 =
0/
1'
03
11
#250
b101 8
0!
09
0>
#255
1!
19
1>
b11000000 K
b1111111 =
1&
02
10
#260
b110 8
0!
09
0>
#265
1!
19
1>
1J
b10000000 K
b11111111 =
1/
1%
01
#270
b111 8
0!
09
0>
#275
1!
19
1>
b0 K
00
#280
b1000 8
1"
0!
1:
1?
09
0>
0J
b0 =
0/
0,
0+
0*
0)
0(
0'
0&
0%
#285
1!
19
1>
#290
0"
1$
b11001010 .
1-
0!
1<
1A
0I
1F
0E
0D
1C
1@
0:
0?
09
0>
#295
1!
19
1>
b11001010 K
b10000000 =
1%
16
14
11
10
#300
0-
b0 8
0!
0@
09
0>
#305
1!
19
1>
b1100101 K
b11000000 =
1&
17
06
15
04
12
00
#310
b1 8
0!
09
0>
#315
1!
19
1>
1J
b110010 K
b11100000 =
1/
1'
07
16
05
13
01
#320
b10 8
0!
09
0>
#325
1!
19
1>
0J
b11001 K
b11110000 =
0/
1(
17
06
14
02
#330
b11 8
0!
09
0>
#335
1!
19
1>
1J
b1100 K
b11111000 =
1/
1)
07
15
03
#340
b100 8
0!
09
0>
#345
1!
19
1>
0J
b110 K
b11111100 =
0/
1*
16
04
#350
b101 8
0!
09
0>
#355
1!
19
1>
b11 K
b11111110 =
1+
17
05
#360
b110 8
0!
09
0>
#365
1!
19
1>
1J
b1 K
b11111111 =
1/
1,
06
#370
b111 8
0!
09
0>
#375
1!
19
1>
b0 K
07
