piso.v
// PISO - Parallel In Serial Out (Shift Left & Shift Right)
module piso(
    input clk, reset,
    input load,           // 1 = load parallel data, 0 = shift
    input shift_dir,      // 0 = shift left, 1 = shift right
    input [7:0] parallel_in,
    output reg serial_out,
    output reg [7:0] reg_state
);
    always @(posedge clk or posedge reset) begin
        if(reset) begin
            reg_state  <= 8'b0;
            serial_out <= 0;
        end
        else if(load) begin
            reg_state  <= parallel_in;  // load parallel data
            serial_out <= 0;
        end
        else begin
            if(shift_dir == 0) begin
                serial_out <= reg_state[7];           // MSB out
                reg_state  <= {reg_state[6:0], 1'b0}; // shift left
            end else begin
                serial_out <= reg_state[0];           // LSB out
                reg_state  <= {1'b0, reg_state[7:1]}; // shift right
            end
        end
    end
endmodule

sipo.v
// SIPO - Serial In Parallel Out (Shift Left & Shift Right)
module sipo(
    input clk, reset,
    input serial_in,
    input shift_dir,      // 0 = shift left, 1 = shift right
    output reg [7:0] parallel_out
);
    always @(posedge clk or posedge reset) begin
        if(reset)
            parallel_out <= 8'b0;
        else if(shift_dir == 0)
            parallel_out <= {parallel_out[6:0], serial_in};  // shift left
        else
            parallel_out <= {serial_in, parallel_out[7:1]};  // shift right
    end
endmodule

shift_register_tb.v
`timescale 1ns/1ns

module shift_register_tb;

    // ---- SIPO signals ----
    reg clk, reset;
    reg serial_in, shift_dir;
    wire [7:0] sipo_out;

    // ---- PISO signals ----
    reg load;
    reg [7:0] parallel_in;
    wire piso_serial_out;
    wire [7:0] piso_state;

    // Instantiate SIPO
    sipo SIPO_inst(
        .clk(clk), .reset(reset),
        .serial_in(serial_in),
        .shift_dir(shift_dir),
        .parallel_out(sipo_out)
    );

    // Instantiate PISO
    piso PISO_inst(
        .clk(clk), .reset(reset),
        .load(load),
        .shift_dir(shift_dir),
        .parallel_in(parallel_in),
        .serial_out(piso_serial_out),
        .reg_state(piso_state)
    );

    // Clock: toggle every 5ns -> 10ns period
    always #5 clk = ~clk;

    integer i;

    initial begin
        $dumpfile("shift_register.vcd");
        $dumpvars(0, shift_register_tb);

        // Init
        clk = 0; reset = 1; serial_in = 0;
        shift_dir = 0; load = 0; parallel_in = 8'b0;
        #10 reset = 0;

        // ============================================
        // SIPO - SHIFT LEFT
        // Serially input 1,0,1,1,0,0,1,1 -> expect 10110011
        // ============================================
        $display("\n--- SIPO Shift LEFT ---");
        shift_dir = 0;
        begin
            serial_in = 1; #10; $display("SIPO SL: serial_in=%b -> parallel_out=%b", serial_in, sipo_out);
            serial_in = 0; #10; $display("SIPO SL: serial_in=%b -> parallel_out=%b", serial_in, sipo_out);
            serial_in = 1; #10; $display("SIPO SL: serial_in=%b -> parallel_out=%b", serial_in, sipo_out);
            serial_in = 1; #10; $display("SIPO SL: serial_in=%b -> parallel_out=%b", serial_in, sipo_out);
            serial_in = 0; #10; $display("SIPO SL: serial_in=%b -> parallel_out=%b", serial_in, sipo_out);
            serial_in = 0; #10; $display("SIPO SL: serial_in=%b -> parallel_out=%b", serial_in, sipo_out);
            serial_in = 1; #10; $display("SIPO SL: serial_in=%b -> parallel_out=%b", serial_in, sipo_out);
            serial_in = 1; #10; $display("SIPO SL: serial_in=%b -> parallel_out=%b", serial_in, sipo_out);
        end

        // Reset before next test
        reset = 1; #10; reset = 0;

        // ============================================
        // SIPO - SHIFT RIGHT
        // ============================================
        $display("\n--- SIPO Shift RIGHT ---");
        shift_dir = 1;
        begin
            serial_in = 1; #10; $display("SIPO SR: serial_in=%b -> parallel_out=%b", serial_in, sipo_out);
            serial_in = 1; #10; $display("SIPO SR: serial_in=%b -> parallel_out=%b", serial_in, sipo_out);
            serial_in = 0; #10; $display("SIPO SR: serial_in=%b -> parallel_out=%b", serial_in, sipo_out);
            serial_in = 0; #10; $display("SIPO SR: serial_in=%b -> parallel_out=%b", serial_in, sipo_out);
            serial_in = 1; #10; $display("SIPO SR: serial_in=%b -> parallel_out=%b", serial_in, sipo_out);
            serial_in = 1; #10; $display("SIPO SR: serial_in=%b -> parallel_out=%b", serial_in, sipo_out);
            serial_in = 0; #10; $display("SIPO SR: serial_in=%b -> parallel_out=%b", serial_in, sipo_out);
            serial_in = 1; #10; $display("SIPO SR: serial_in=%b -> parallel_out=%b", serial_in, sipo_out);
        end

        // Reset before PISO
        reset = 1; #10; reset = 0;

        // ============================================
        // PISO - SHIFT LEFT
        // Load 10110011, then shift out serially
        // ============================================
        $display("\n--- PISO Shift LEFT (load=10110011) ---");
        shift_dir = 0;
        parallel_in = 8'b10110011;
        load = 1; #10; load = 0;
        $display("PISO loaded: reg_state=%b", piso_state);
        for(i = 0; i < 8; i = i+1) begin
            #10;
            $display("PISO SL: serial_out=%b | reg_state=%b", piso_serial_out, piso_state);
        end

        // Reset before next PISO test
        reset = 1; #10; reset = 0;

        // ============================================
        // PISO - SHIFT RIGHT
        // Load 11001010, then shift out serially
        // ============================================
        $display("\n--- PISO Shift RIGHT (load=11001010) ---");
        shift_dir = 1;
        parallel_in = 8'b11001010;
        load = 1; #10; load = 0;
        $display("PISO loaded: reg_state=%b", piso_state);
        for(i = 0; i < 8; i = i+1) begin
            #10;
            $display("PISO SR: serial_out=%b | reg_state=%b", piso_serial_out, piso_state);
        end

        $finish;
    end

endmodule

shift_register.vcd
$date
	Fri Apr 24 10:07:24 2026
$end
$version
	Icarus Verilog
$end
$timescale
	1ns
$end
$scope module shift_register_tb $end
$var wire 8 ! sipo_out [7:0] $end
$var wire 8 " piso_state [7:0] $end
$var wire 1 # piso_serial_out $end
$var reg 1 $ clk $end
$var reg 1 % load $end
$var reg 8 & parallel_in [7:0] $end
$var reg 1 ' reset $end
$var reg 1 ( serial_in $end
$var reg 1 ) shift_dir $end
$var integer 32 * i [31:0] $end
$scope module PISO_inst $end
$var wire 1 $ clk $end
$var wire 1 % load $end
$var wire 8 + parallel_in [7:0] $end
$var wire 1 ' reset $end
$var wire 1 ) shift_dir $end
$var reg 8 , reg_state [7:0] $end
$var reg 1 # serial_out $end
$upscope $end
$scope module SIPO_inst $end
$var wire 1 $ clk $end
$var wire 1 ' reset $end
$var wire 1 ( serial_in $end
$var wire 1 ) shift_dir $end
$var reg 8 - parallel_out [7:0] $end
$upscope $end
$upscope $end
$enddefinitions $end
$comment Show the parameter values. $end
$dumpall
$end
#0
$dumpvars
b0 -
b0 ,
b0 +
bx *
0)
0(
1'
b0 &
0%
0$
0#
b0 "
b0 !
$end
#5
1$
#10
0$
1(
0'
#15
b1 !
b1 -
1$
#20
0$
0(
#25
b10 !
b10 -
1$
#30
0$
1(
#35
b101 !
b101 -
1$
#40
0$
#45
b1011 !
b1011 -
1$
#50
0$
0(
#55
b10110 !
b10110 -
1$
#60
0$
#65
b101100 !
b101100 -
1$
#70
0$
1(
#75
b1011001 !
b1011001 -
1$
#80
0$
#85
b10110011 !
b10110011 -
1$
#90
b0 !
b0 -
0$
1'
#95
1$
#100
0$
1)
0'
#105
b10000000 !
b10000000 -
1$
#110
0$
#115
b11000000 !
b11000000 -
1$
#120
0$
0(
#125
b1100000 !
b1100000 -
1$
#130
0$
#135
b110000 !
b110000 -
1$
#140
0$
1(
#145
b10011000 !
b10011000 -
1$
#150
0$
#155
b11001100 !
b11001100 -
1$
#160
0$
0(
#165
b1100110 !
b1100110 -
1$
#170
0$
1(
#175
b10110011 !
b10110011 -
1$
#180
b0 !
b0 -
0$
1'
#185
1$
#190
0$
1%
b10110011 &
b10110011 +
0)
0'
#195
b1 !
b1 -
b10110011 "
b10110011 ,
1$
#200
0$
b0 *
0%
#205
b1100110 "
b1100110 ,
1#
b11 !
b11 -
1$
#210
0$
b1 *
#215
b111 !
b111 -
b11001100 "
b11001100 ,
0#
1$
#220
0$
b10 *
#225
b10011000 "
b10011000 ,
1#
b1111 !
b1111 -
1$
#230
0$
b11 *
#235
b11111 !
b11111 -
b110000 "
b110000 ,
1$
#240
0$
b100 *
#245
b1100000 "
b1100000 ,
0#
b111111 !
b111111 -
1$
#250
0$
b101 *
#255
b1111111 !
b1111111 -
b11000000 "
b11000000 ,
1$
#260
0$
b110 *
#265
b10000000 "
b10000000 ,
1#
b11111111 !
b11111111 -
1$
#270
0$
b111 *
#275
b0 "
b0 ,
1$
#280
0#
b0 !
b0 -
0$
1'
b1000 *
#285
1$
#290
0$
1%
b11001010 &
b11001010 +
1)
0'
#295
b11001010 "
b11001010 ,
b10000000 !
b10000000 -
1$
#300
0$
b0 *
0%
#305
b11000000 !
b11000000 -
b1100101 "
b1100101 ,
1$
#310
0$
b1 *
#315
b110010 "
b110010 ,
1#
b11100000 !
b11100000 -
1$
#320
0$
b10 *
#325
b11110000 !
b11110000 -
b11001 "
b11001 ,
0#
1$
#330
0$
b11 *
#335
b1100 "
b1100 ,
1#
b11111000 !
b11111000 -
1$
#340
0$
b100 *
#345
b11111100 !
b11111100 -
b110 "
b110 ,
0#
1$
#350
0$
b101 *
#355
b11 "
b11 ,
b11111110 !
b11111110 -
1$
#360
0$
b110 *
#365
b11111111 !
b11111111 -
b1 "
b1 ,
1#
1$
#370
0$
b111 *
#375
b0 "
b0 ,
1$
#380
0$
b1000 *
